jwe/__init__.py
jwe/backend.py
jwe/decryption.py
jwe/encryption.py
jwe/exceptions.py
jwe/util.py
jwe/validation.py
PyJWE-0.1.6.dist-info/DESCRIPTION.rst
PyJWE-0.1.6.dist-info/METADATA
PyJWE-0.1.6.dist-info/metadata.json
PyJWE-0.1.6.dist-info/pbr.json
PyJWE-0.1.6.dist-info/RECORD
PyJWE-0.1.6.dist-info/top_level.txt
PyJWE-0.1.6.dist-info/WHEEL
