Metadata-Version: 2.0
Name: PyJWE
Version: 0.1.6
Summary: JSON Web Encryption implementation in Python
Home-page: http://github.com/chrisseto/pyjwe
Author: UNKNOWN
Author-email: UNKNOWN
License: MIT
Keywords: jwe json encryption token security signing
Platform: UNKNOWN
Classifier: Intended Audience :: Developers
Classifier: Natural Language :: English
Classifier: License :: OSI Approved :: MIT License
Classifier: Programming Language :: Python
Classifier: Programming Language :: Python :: 2.6
Classifier: Programming Language :: Python :: 2.7
Classifier: Programming Language :: Python :: 3.3
Classifier: Programming Language :: Python :: 3.4
Classifier: Topic :: Utilities
Requires-Dist: cryptography (>=0.9.3)
